[
  {
    "ContainingType": "Tech_Manage_Server.Controllers.AccountController",
    "Method": "Login",
    "RelativePath": "api/Account/Login",
    "HttpMethod": "POST",
    "IsController": true,
    "Order": 0,
    "Parameters": [
      {
        "Name": "model",
        "Type": "Tech_Manage_Server.DTOs.Auths.LoginDto",
        "IsRequired": true
      }
    ],
    "ReturnTypes": []
  },
  {
    "ContainingType": "Tech_Manage_Server.Controllers.AccountController",
    "Method": "Register",
    "RelativePath": "api/Account/Register",
    "HttpMethod": "POST",
    "IsController": true,
    "Order": 0,
    "Parameters": [
      {
        "Name": "model",
        "Type": "Tech_Manage_Server.DTOs.Auth.RegisterDto",
        "IsRequired": true
      }
    ],
    "ReturnTypes": []
  },
  {
    "ContainingType": "Tech_Manage_Server.Controllers.RepairController",
    "Method": "CreateRepair",
    "RelativePath": "api/CreateRepair",
    "HttpMethod": "POST",
    "IsController": true,
    "Order": 0,
    "Parameters": [
      {
        "Name": "createRepairDto",
        "Type": "Tech_Manage_Server.DTOs.CreateRepairDto",
        "IsRequired": true
      }
    ],
    "ReturnTypes": [
      {
        "Type": "Tech_Manage_Server.Models.Repair",
        "MediaTypes": [
          "text/plain",
          "application/json",
          "text/json"
        ],
        "StatusCode": 200
      }
    ]
  },
  {
    "ContainingType": "Tech_Manage_Server.Controllers.RepairController",
    "Method": "GetAllRepair",
    "RelativePath": "api/GetAllRepair",
    "HttpMethod": "GET",
    "IsController": true,
    "Order": 0,
    "Parameters": [],
    "ReturnTypes": [
      {
        "Type": "System.Collections.Generic.List\u00601[[Tech_Manage_Server.Models.Repair, Tech_Manage_Server, Version=1.0.0.0, Culture=neutral, PublicKeyToken=null]]",
        "MediaTypes": [
          "text/plain",
          "application/json",
          "text/json"
        ],
        "StatusCode": 200
      }
    ]
  },
  {
    "ContainingType": "Tech_Manage_Server.Controllers.RepairController",
    "Method": "GetRepairById",
    "RelativePath": "api/GetRepairById/{id}",
    "HttpMethod": "GET",
    "IsController": true,
    "Order": 0,
    "Parameters": [
      {
        "Name": "id",
        "Type": "System.Int32",
        "IsRequired": true
      }
    ],
    "ReturnTypes": [
      {
        "Type": "Tech_Manage_Server.Models.Repair",
        "MediaTypes": [
          "text/plain",
          "application/json",
          "text/json"
        ],
        "StatusCode": 200
      }
    ]
  },
  {
    "ContainingType": "Tech_Manage_Server.Controllers.RepairController",
    "Method": "UpdateRepair",
    "RelativePath": "api/UpdateRepair/{id}",
    "HttpMethod": "PUT",
    "IsController": true,
    "Order": 0,
    "Parameters": [
      {
        "Name": "id",
        "Type": "System.Int32",
        "IsRequired": true
      },
      {
        "Name": "updateRepairDto",
        "Type": "Tech_Manage_Server.DTOs.UpdateRepairDto",
        "IsRequired": true
      }
    ],
    "ReturnTypes": [
      {
        "Type": "Tech_Manage_Server.Models.Repair",
        "MediaTypes": [
          "text/plain",
          "application/json",
          "text/json"
        ],
        "StatusCode": 200
      }
    ]
  }
]